pihello/__init__.py
pihello/cli.py
pihello/color.py
pihello/color_tables.py
pihello/console.py
pihello/style.py
pihello-0.3.0.dist-info/METADATA
pihello-0.3.0.dist-info/WHEEL
pihello-0.3.0.dist-info/entry_points.txt
pihello-0.3.0.dist-info/RECORD
