Metadata-Version: 2.1
Name: pihello
Version: 0.3.0
Summary: Highly configurable and scriptable Pi-hole statistics in text
Home-page: https://github.com/pavelgar/Pi-hello
License: MIT
Keywords: command-line-tool,pi-hole,stats,pihello
Author: pavelgar
Author-email: pavel.garmuyev@gmail.com
Requires-Python: >=3.8,<4.0
Classifier: License :: OSI Approved :: MIT License
Classifier: Programming Language :: Python :: 3
Classifier: Programming Language :: Python :: 3.8
Classifier: Programming Language :: Python :: 3.9
Classifier: Programming Language :: Python :: 3.10
Classifier: Programming Language :: Python :: 3.11
Project-URL: Repository, https://github.com/pavelgar/Pi-hello
